{
  "id": "aus.003.ele",
  "display": "Eleanor Tilney",
  "unique_words": "45",
  "speeches": "77",
  "words": {
    "embellishments": "2",
    "agricola": "1",
    "alfred": "1",
    "alice": "1",
    "beforehand": "1",
    "blair": "1",
    "bonnets": "1",
    "brute": "1",
    "caractacus": "1",
    "conclude": "1",
    "courting": "1",
    "cover": "1",
    "curious": "1",
    "diction": "1",
    "discomposed": "1",
    "distracts": "1",
    "endears": "1",
    "extenuation": "1",
    "hermitage": "1",
    "histories": "1",
    "holding": "1",
    "hume": "1",
    "importune": "1",
    "incorrectness": "1",
    "intolerable": "1",
    "johnson": "1",
    "meditate": "1",
    "nominal": "1",
    "overpowered": "1",
    "painting": "1",
    "production": "1",
    "raising": "1",
    "records": "1",
    "risks": "1",
    "robertson": "1",
    "ruffle": "1",
    "seventy": "1",
    "sources": "1",
    "unattended": "1",
    "undertook": "1",
    "unprincipled": "1",
    "violating": "1",
    "waters": "1",
    "wisest": "1",
    "worst": "1"
  }
}