{
  "unique_words": "63",
  "speeches": "83",
  "words": {
    "charles": "7",
    "mother-in-law": "2",
    "presume": "2",
    "abound": "1",
    "annoyed": "1",
    "attitude": "1",
    "beaux": "1",
    "blots": "1",
    "blowsy": "1",
    "brings": "1",
    "brown": "1",
    "build": "1",
    "buying": "1",
    "coarse": "1",
    "comfortless": "1",
    "compass": "1",
    "country-town": "1",
    "crowd": "1",
    "cure": "1",
    "deprive": "1",
    "despair": "1",
    "despises": "1",
    "device": "1",
    "exception": "1",
    "exquisite": "1",
    "gets": "1",
    "grantley": "1",
    "great-uncle": "1",
    "half-deserved": "1",
    "harp": "1",
    "hating": "1",
    "hotel": "1",
    "hug": "1",
    "implicit": "1",
    "indulging": "1",
    "insipidity": "1",
    "inspires": "1",
    "insufferably": "1",
    "languages": "1",
    "lease": "1",
    "misleading": "1",
    "nose": "1",
    "nothingness": "1",
    "painter": "1",
    "pens": "1",
    "possesses": "1",
    "possibilities": "1",
    "process": "1",
    "reverie": "1",
    "scampering": "1",
    "self-sufficiency": "1",
    "shrewish": "1",
    "strictures": "1",
    "succeeds": "1",
    "suffers": "1",
    "surpass": "1",
    "tedious": "1",
    "teeth": "1",
    "undervaluing": "1",
    "untidy": "1",
    "using": "1",
    "waking": "1",
    "writes": "1"
  }
}